{
  "main": {
    "id": "5401f1952ac34617",
    "type": "split",
    "children": [
      {
        "id": "abd7762b2f97378e",
        "type": "tabs",
        "children": [
          {
            "id": "df3f3ea63f184b0c",
            "type": "leaf",
            "state": {
              "type": "canvas",
              "state": {
                "file": "Технические моменты.canvas",
                "viewState": {
                  "x": -641.1056533493474,
                  "y": -107.23980591131146,
                  "zoom": 0.13299126742797984
                }
              },
              "icon": "lucide-layout-dashboard",
              "title": "Технические моменты"
            }
          }
        ]
      }
    ],
    "direction": "vertical"
  },
  "left": {
    "id": "884c03097c36a7ce",
    "type": "split",
    "children": [
      {
        "id": "3d80a1aee427d383",
        "type": "tabs",
        "children": [
          {
            "id": "e3adcbe4f5c4c1a9",
            "type": "leaf",
            "state": {
              "type": "file-explorer",
              "state": {
                "sortOrder": "alphabetical",
                "autoReveal": false
              },
              "icon": "lucide-folder-closed",
              "title": "Файловый менеджер"
            }
          },
          {
            "id": "a6ef679b416e87c4",
            "type": "leaf",
            "state": {
              "type": "search",
              "state": {
                "query": "",
                "matchingCase": false,
                "explainSearch": false,
                "collapseAll": false,
                "extraContext": false,
                "sortOrder": "alphabetical"
              },
              "icon": "lucide-search",
              "title": "Поиск"
            }
          },
          {
            "id": "f20cd60c59819bc3",
            "type": "leaf",
            "state": {
              "type": "bookmarks",
              "state": {},
              "icon": "lucide-bookmark",
              "title": "Закладки"
            }
          }
        ]
      }
    ],
    "direction": "horizontal",
    "width": 300
  },
  "right": {
    "id": "dfc194c83806b6d1",
    "type": "split",
    "children": [
      {
        "id": "54eaeab90a8c7300",
        "type": "tabs",
        "children": [
          {
            "id": "b785aeb2e7f1a06d",
            "type": "leaf",
            "state": {
              "type": "backlink",
              "state": {
                "file": "Добро пожаловать.md",
                "collapseAll": false,
                "extraContext": false,
                "sortOrder": "alphabetical",
                "showSearch": false,
                "searchQuery": "",
                "backlinkCollapsed": false,
                "unlinkedCollapsed": true
              },
              "icon": "links-coming-in",
              "title": "Обратные ссылки для Добро пожаловать"
            }
          },
          {
            "id": "8773db474ad52b86",
            "type": "leaf",
            "state": {
              "type": "outgoing-link",
              "state": {
                "file": "Добро пожаловать.md",
                "linksCollapsed": false,
                "unlinkedCollapsed": true
              },
              "icon": "links-going-out",
              "title": "Исходящие ссылки из Добро пожаловать"
            }
          },
          {
            "id": "4dc511b772fd306f",
            "type": "leaf",
            "state": {
              "type": "tag",
              "state": {
                "sortOrder": "frequency",
                "useHierarchy": true,
                "showSearch": false,
                "searchQuery": ""
              },
              "icon": "lucide-tags",
              "title": "Теги"
            }
          },
          {
            "id": "bd6279c4ecb17c1d",
            "type": "leaf",
            "state": {
              "type": "all-properties",
              "state": {
                "sortOrder": "frequency",
                "showSearch": false,
                "searchQuery": ""
              },
              "icon": "lucide-archive",
              "title": "Все свойства"
            }
          },
          {
            "id": "2d579040bb8b2557",
            "type": "leaf",
            "state": {
              "type": "outline",
              "state": {
                "file": "Добро пожаловать.md",
                "followCursor": false,
                "showSearch": false,
                "searchQuery": ""
              },
              "icon": "lucide-list",
              "title": "Структура Добро пожаловать"
            }
          }
        ]
      }
    ],
    "direction": "horizontal",
    "width": 300,
    "collapsed": true
  },
  "left-ribbon": {
    "hiddenItems": {
      "switcher:Меню быстрого перехода": false,
      "graph:Граф": false,
      "canvas:Создать новый холст": false,
      "daily-notes:Сегодняшняя заметка": false,
      "templates:Вставить шаблон": false,
      "command-palette:Открыть палитру команд": false,
      "bases:Создать новую базу": false
    }
  },
  "active": "df3f3ea63f184b0c",
  "lastOpenFiles": [
    "Сюжетные моменты.canvas",
    "Краткий пересказ главы 1.md",
    "Детали внешности Милы.md",
    "холст в миро.canvas",
    "Технические моменты.canvas",
    "План глав.md",
    "Персонажи.canvas",
    "Переменная инициативы в отношениях.md",
    "Мила (ГГ).md",
    "Удалось спасти.md",
    "Не удалось спасти.md",
    "Без названия.base",
    "2026-05-17.md",
    "Добро пожаловать.md"
  ]
}